[
  {
    "id": 1,
    "question": "न्यूटन के गति के नियम के अनुसार, यदि कोई बाहरी बल नहीं लगता है, तो वस्तु क्या करती है?",
    "options": [
      "A) अपनी स्थिति में रहती है",
      "B) गति में परिवर्तन होता है",
      "C) दिशा बदलती है",
      "D) रुक जाती है"
    ],
    "correct": "A",
    "explanation": "न्यूटन के गति के नियम के अनुसार, यदि कोई बाहरी बल नहीं लगता है, तो वस्तु अपनी स्थिति में रहती है।"
  },
  {
    "id": 2,
    "question": "गेंद की गति में परिवर्तन का क्या कारण है?",
    "options": [
      "A) केवल बल के कारण",
      "B) केवल द्रव्यमान के कारण",
      "C) बल और द्रव्यमान के कारण",
      "D) कोई नहीं"
    ],
    "correct": "C",
    "explanation": "गेंद की गति में परिवर्तन बल और द्रव्यमान के कारण होता है।"
  },
  {
    "id": 3,
    "question": "न्यूटन के गति के नियम के तीसरे नियम के अनुसार, हर क्रिया की क्या होती है?",
    "options": [
      "A) एक असमान प्रतिक्रिया",
      "B) एक समान और विरुद्ध प्रतिक्रिया",
      "C) कोई प्रतिक्रिया नहीं",
      "D) एक समान प्रतिक्रिया"
    ],
    "correct": "B",
    "explanation": "न्यूटन के गति के नियम के तीसरे नियम के अनुसार, हर क्रिया की एक समान और विरुद्ध प्रतिक्रिया होती है।"
  },
  {
    "id": 4,
    "question": "रोहन ने गेंद को किक मारा और वह तेजी से चली गई, इसका क्या कारण है?",
    "options": [
      "A) गेंद का द्रव्यमान कम होना",
      "B) रोहन का बल अधिक होना",
      "C) गेंद की गति पहले से अधिक होना",
      "D) सभी विकल्प सही हैं"
    ],
    "correct": "B",
    "explanation": "रोहन ने गेंद को किक मारा और वह तेजी से चली गई, इसका कारण रोहन का बल अधिक होना है।"
  },
  {
    "id": 5,
    "question": "न्यूटन के गति के नियम के अनुसार, वस्तु की स्थिति में परिवर्तन क्या निर्भर करता है?",
    "options": [
      "A) केवल बल पर",
      "B) केवल द्रव्यमान पर",
      "C) बल और द्रव्यमान पर",
      "D) किसी पर नहीं"
    ],
    "correct": "C",
    "explanation": "न्यूटन के गति के नियम के अनुसार, वस्तु की स्थिति में परिवर्तन बल और द्रव्यमान पर निर्भर करता है।"
  }
]